reportWayson/HTMLTestRunner.py
reportWayson/PyTestReportPlug.py
reportWayson/SendEmail.py
reportWayson/__init__.py
reportWayson/api.py
reportWayson/static/css/default.css
reportWayson/static/css/legency.css
reportWayson/static/js/capture.js
reportWayson/static/js/default.js
reportWayson/static/js/legency.js
reportWayson/templates/default.html
reportWayson/templates/legency.html
reportWaysonQ/HTMLTestRunner.py
reportWaysonQ/PyTestReportPlug.py
reportWaysonQ/SendEmail.py
reportWaysonQ/__init__.py
reportWaysonQ/api.py
reportWaysonQ/static/css/default.css
reportWaysonQ/static/css/legency.css
reportWaysonQ/static/js/capture.js
reportWaysonQ/static/js/default.js
reportWaysonQ/static/js/legency.js
reportWaysonQ/templates/default.html
reportWaysonQ/templates/legency.html
reportWaysonQQ/HTMLTestRunner.py
reportWaysonQQ/PyTestReportPlug.py
reportWaysonQQ/SendEmail.py
reportWaysonQQ/__init__.py
reportWaysonQQ/api.py
reportWaysonQQ/static/css/default.css
reportWaysonQQ/static/css/legency.css
reportWaysonQQ/static/js/capture.js
reportWaysonQQ/static/js/default.js
reportWaysonQQ/static/js/legency.js
reportWaysonQQ/templates/default.html
reportWaysonQQ/templates/legency.html
reportWaysonQQQ/HTMLTestRunner.py
reportWaysonQQQ/PyTestReportPlug.py
reportWaysonQQQ/SendEmail.py
reportWaysonQQQ/__init__.py
reportWaysonQQQ/api.py
reportWaysonQQQ/static/css/default.css
reportWaysonQQQ/static/css/legency.css
reportWaysonQQQ/static/js/capture.js
reportWaysonQQQ/static/js/default.js
reportWaysonQQQ/static/js/legency.js
reportWaysonQQQ/templates/default.html
reportWaysonQQQ/templates/legency.html
reportWaysonQi/HTMLTestRunner.py
reportWaysonQi/PyTestReportPlug.py
reportWaysonQi/SendEmail.py
reportWaysonQi/__init__.py
reportWaysonQi/api.py
reportWaysonQi/static/css/default.css
reportWaysonQi/static/css/legency.css
reportWaysonQi/static/js/capture.js
reportWaysonQi/static/js/default.js
reportWaysonQi/static/js/legency.js
reportWaysonQi/templates/default.html
reportWaysonQi-1.2.1.dist-info/LICENCE
reportWaysonQi-1.2.1.dist-info/METADATA
reportWaysonQi-1.2.1.dist-info/WHEEL
reportWaysonQi-1.2.1.dist-info/entry_points.txt
reportWaysonQi-1.2.1.dist-info/top_level.txt
reportWaysonQi-1.2.1.dist-info/RECORD
