Metadata-Version: 2.1
Name: reportWaysonQi
Version: 1.2.1
Summary: UNKNOWN
Home-page: UNKNOWN
Author: 
Author-email: 
License: UNKNOWN
Keywords: test report,python unit testing
Platform: any
Classifier: Programming Language :: Python :: 3
Classifier: License :: OSI Approved :: MIT License
Classifier: Operating System :: OS Independent
Classifier: Framework :: Pytest
Requires-Dist: Jinja2 (==2.10)
Requires-Dist: Flask (==1.0.2)
